PhysioKit2/__init__.py
PhysioKit2/form.ui
PhysioKit2/form_ui.py
PhysioKit2/main.py
PhysioKit2/register_dummy.py
PhysioKit2/analysis_helper/__init__.py
PhysioKit2/analysis_helper/process_signals.py
PhysioKit2/analysis_helper/sample_data/__init__.py
PhysioKit2/analysis_helper/sample_data/download data from PhysioKit GitHub repo page.txt
PhysioKit2/analysis_helper/utils/__init__.py
PhysioKit2/analysis_helper/utils/load_data.py
PhysioKit2/configs/__init__.py
PhysioKit2/configs/exp_config_phys.json
PhysioKit2/configs/arm_due/__init__.py
PhysioKit2/configs/arm_due/sw_config.json
PhysioKit2/configs/arm_due/sw_config_client.json
PhysioKit2/configs/arm_due/sw_config_server.json
PhysioKit2/configs/avr_default/__init__.py
PhysioKit2/configs/avr_default/sw_config.json
PhysioKit2/configs/avr_default/sw_config_client.json
PhysioKit2/configs/avr_default/sw_config_server.json
PhysioKit2/images/__init__.py
PhysioKit2/images/banner.png
PhysioKit2/images/color_bar.png
PhysioKit2/images/sq_indication.png
PhysioKit2/sqa/__init__.py
PhysioKit2/sqa/inference.py
PhysioKit2/sqa/inference_thread.py
PhysioKit2/sqa/ckpt/SQAPhysMD.pth
PhysioKit2/sqa/ckpt/__init__.py
PhysioKit2/sqa/config/SQAPhysMD.json
PhysioKit2/sqa/config/__init__.py
PhysioKit2/sqa/model/SQAPhysMD.py
PhysioKit2/sqa/model/__init__.py
PhysioKit2/utils/__init__.py
PhysioKit2/utils/acquisition.py
PhysioKit2/utils/biofeedback.py
PhysioKit2/utils/config.py
PhysioKit2/utils/data_processing_lib.py
PhysioKit2/utils/external_sync.py
PhysioKit2/utils/file_ops.py
PhysioKit2/utils/load_data.py
PhysioKit2-2.1.0.dist-info/LICENSE
PhysioKit2-2.1.0.dist-info/METADATA
PhysioKit2-2.1.0.dist-info/WHEEL
PhysioKit2-2.1.0.dist-info/entry_points.txt
PhysioKit2-2.1.0.dist-info/top_level.txt
PhysioKit2-2.1.0.dist-info/RECORD
