Metadata-Version: 2.1
Name: PhysioKit2
Version: 2.1.0
Summary: PhysioKit: An Open-Source, Low-Cost Physiological Computing Toolkit for Single- and Multi-User Studies
Home-page: https://github.com/PhysiologicAILab/PhysioKit
Author: ['Jitesh Joshi', 'Katherine wang', 'Youngjun Cho']
Author-email: youngjun.cho@ucl.ac.uk
License: MIT
License-File: LICENSE
Requires-Dist: matplotlib
Requires-Dist: neurokit2
Requires-Dist: numpy
Requires-Dist: opencv-contrib-python
Requires-Dist: pyserial
Requires-Dist: PySide6
Requires-Dist: PySide6-Addons
Requires-Dist: PySide6-Essentials
Requires-Dist: scipy
Requires-Dist: pandas
Requires-Dist: torch
Requires-Dist: setuptools
Requires-Dist: requests
